nemo_library_ui/__init__.py
nemo_library_ui/__main__.py
nemo_library_ui/ui.py
nemo_library_ui/version.py
nemo_library_ui-0.1.1.dist-info/licenses/LICENSE
nemo_library_ui-0.1.1.dist-info/METADATA
nemo_library_ui-0.1.1.dist-info/WHEEL
nemo_library_ui-0.1.1.dist-info/entry_points.txt
nemo_library_ui-0.1.1.dist-info/top_level.txt
nemo_library_ui-0.1.1.dist-info/RECORD
